turboo/__init__.py
turboo/__main__.py
turboo-0.0.3.dist-info/LICENSE
turboo-0.0.3.dist-info/METADATA
turboo-0.0.3.dist-info/WHEEL
turboo-0.0.3.dist-info/top_level.txt
turboo-0.0.3.dist-info/RECORD
