Metadata-Version: 2.1
Name: turboo
Version: 0.0.3
Summary: REST-based same-host octoprint cli in python
Author-email: Robert Degen <turbodev@mailbox.org>
Project-URL: Homepage, https://github.com/turbo-bert/o
Project-URL: Issues, https://github.com/turbo-bert/o/issues
Classifier: Programming Language :: Python :: 3
Classifier: License :: OSI Approved :: MIT License
Classifier: Operating System :: OS Independent
Requires-Python: >=3.8
License-File: LICENSE
Requires-Dist: requests
